{
  "applications": "*",
  "changelogDate": "20230125233217",
  "clientRootFolder": "invoice",
  "databaseType": "sql",
  "dto": "no",
  "embedded": false,
  "entityTableName": "shipment",
  "fields": [
    {
      "fieldName": "trackingCode",
      "fieldType": "String"
    },
    {
      "fieldName": "date",
      "fieldType": "Instant",
      "fieldValidateRules": ["required"]
    },
    {
      "fieldName": "details",
      "fieldType": "String"
    }
  ],
  "fluentMethods": true,
  "jpaMetamodelFiltering": false,
  "microserviceName": "invoice",
  "name": "Shipment",
  "pagination": "pagination",
  "readOnly": false,
  "relationships": [
    {
      "otherEntityName": "invoice",
      "otherEntityRelationshipName": "shipment",
      "relationshipName": "invoice",
      "relationshipType": "many-to-one"
    }
  ],
  "service": "no"
}
